app/__init__.py
sleekify/__init__.py
sleekify/_types.py
sleekify/const.py
sleekify/guards.py
sleekify/requests.py
sleekify/responses.py
sleekify/router.py
sleekify/util.py
sleekify-0.0.21.dist-info/METADATA
sleekify-0.0.21.dist-info/WHEEL
sleekify-0.0.21.dist-info/top_level.txt
sleekify-0.0.21.dist-info/RECORD
