Metadata-Version: 2.1
Name: sleekify
Version: 0.0.21
Summary: Sleekify: A minimalistic, ASGI Python framework for building REST API's.
Home-page: https://github.com/0mjs/sleekify
Author: Matt J. Stevenson
Author-email: dev@mattjs.me
Classifier: Programming Language :: Python :: 3
Classifier: License :: OSI Approved :: MIT License
Classifier: Operating System :: OS Independent
Requires-Python: >=3.11
Requires-Dist: pydantic
Requires-Dist: starlette
Requires-Dist: uvicorn
